bear_sync/__init__.py
bear_sync/main.py
bear_sync/sync.py
bear_sync-0.0.1.dist-info/LICENSE
bear_sync-0.0.1.dist-info/METADATA
bear_sync-0.0.1.dist-info/WHEEL
bear_sync-0.0.1.dist-info/entry_points.txt
bear_sync-0.0.1.dist-info/top_level.txt
bear_sync-0.0.1.dist-info/RECORD
