Metadata-Version: 2.2
Name: bear-sync
Version: 0.0.1
Summary: Sync notes from Bear to a local directory
License-File: LICENSE
Requires-Dist: click>=8.1.8
Requires-Dist: importlib-metadata; python_version >= "3.12"
